pc.v
// pc.v - Parameterized Program Counter Register
module pc #(
    parameter PC_WIDTH   = 32,
    parameter RESET_ADDR = 32'h0000_0000
)(
    input  wire                  clk,
    input  wire                  reset,
    input  wire [PC_WIDTH-1:0]   next_pc,
    output reg  [PC_WIDTH-1:0]   current_pc
);

    always @(posedge clk or posedge reset) begin
        if (reset) begin
            current_pc <= RESET_ADDR;
        end else begin
            current_pc <= next_pc;
        end
    end

endmodule

pc_tb.v
// tb_pc.v - Testbench for Parameterized PC
`timescale 1ns/1ps

module tb_pc;

    // Local testbench parameters
    parameter TEST_WIDTH = 32;
    parameter TEST_RESET = 32'h0000_0000;

    reg                     clk;
    reg                     reset;
    reg  [TEST_WIDTH-1:0]   next_pc;
    wire [TEST_WIDTH-1:0]   current_pc;

    // Instantiate PC unit with parameters
    pc #(
        .PC_WIDTH(TEST_WIDTH),
        .RESET_ADDR(TEST_RESET)
    ) uut (
        .clk(clk),
        .reset(reset),
        .next_pc(next_pc),
        .current_pc(current_pc)
    );

    // Clock Generation (100MHz -> 10ns period)
    always #5 clk = ~clk;

    initial begin
        // Dump waveform for GTKWave
        $dumpfile("sim/pc_wave.vcd");
        $dumpvars(0, tb_pc);

        // Initialize signals
        clk = 0;
        reset = 1;
        next_pc = TEST_RESET;

        #12;
        reset = 0; // Release reset

        // Advance PC in steps of 4
        #10 next_pc = current_pc + 32'd4;
        #10 next_pc = current_pc + 32'd4;
        #10 next_pc = current_pc + 32'd4;
        #10 next_pc = current_pc + 32'd4;

        #20;
        $display("Parameterized PC Test Complete!");
        $finish;
    end

endmodule

sim/pc_wave.vcd
$date
	Thu Aug 13 22:39:35 2026
$end
$version
	Icarus Verilog
$end
$timescale
	1ps
$end
$scope module tb_pc $end
$var wire 32 ! current_pc [31:0] $end
$var reg 1 " clk $end
$var reg 32 # next_pc [31:0] $end
$var reg 1 $ reset $end
$scope module uut $end
$var wire 1 " clk $end
$var wire 32 % next_pc [31:0] $end
$var wire 1 $ reset $end
$var reg 32 & current_pc [31:0] $end
$upscope $end
$upscope $end
$enddefinitions $end
#0
$dumpvars
b0 &
b0 %
1$
b0 #
0"
b0 !
$end
#5000
1"
#10000
0"
#12000
0$
#15000
1"
#20000
0"
#22000
b100 #
b100 %
#25000
b100 !
b100 &
1"
#30000
0"
#32000
b1000 #
b1000 %
#35000
b1000 !
b1000 &
1"
#40000
0"
#42000
b1100 #
b1100 %
#45000
b1100 !
b1100 &
1"
#50000
0"
#52000
b10000 #
b10000 %
#55000
b10000 !
b10000 &
1"
