reg_file.v
// reg_file.v - Parameterized 32-Register RISC-V Register File
module reg_file #(
    parameter DATA_WIDTH     = 32,
    parameter REG_ADDR_WIDTH = 5   // 2^5 = 32 registers
)(
    input  wire                     clk,
    input  wire                     reset,
    
    // Write Port
    input  wire                     reg_write,
    input  wire [REG_ADDR_WIDTH-1:0] rd_addr,
    input  wire [DATA_WIDTH-1:0]     rd_data,
    
    // Read Ports
    input  wire [REG_ADDR_WIDTH-1:0] rs1_addr,
    output wire [DATA_WIDTH-1:0]     rs1_data,
    input  wire [REG_ADDR_WIDTH-1:0] rs2_addr,
    output wire [DATA_WIDTH-1:0]     rs2_data
);

    localparam NUM_REGS = 1 << REG_ADDR_WIDTH;

    // 32 registers of DATA_WIDTH size
    reg [DATA_WIDTH-1:0] registers [0:NUM_REGS-1];
    integer i;

    // Synchronous Write Logic
    always @(posedge clk or posedge reset) begin
        if (reset) begin
            for (i = 0; i < NUM_REGS; i = i + 1) begin
                registers[i] <= {DATA_WIDTH{1'b0}};
            end
        end else if (reg_write && (rd_addr != {REG_ADDR_WIDTH{1'b0}})) begin
            // Write data only if reg_write is active and target register is NOT x0
            registers[rd_addr] <= rd_data;
        end
    end

    // Asynchronous Read Logic (x0 hardwired to 0)
    assign rs1_data = (rs1_addr == {REG_ADDR_WIDTH{1'b0}}) ? {DATA_WIDTH{1'b0}} : registers[rs1_addr];
    assign rs2_data = (rs2_addr == {REG_ADDR_WIDTH{1'b0}}) ? {DATA_WIDTH{1'b0}} : registers[rs2_addr];

endmodule

tb_reg_file.v
// tb_reg_file.v - Testbench for Register File
`timescale 1ns/1ps

module tb_reg_file;

    parameter DATA_WIDTH     = 32;
    parameter REG_ADDR_WIDTH = 5;

    reg                      clk;
    reg                      reset;
    reg                      reg_write;
    reg  [REG_ADDR_WIDTH-1:0] rd_addr;
    reg  [DATA_WIDTH-1:0]     rd_data;
    reg  [REG_ADDR_WIDTH-1:0] rs1_addr;
    wire [DATA_WIDTH-1:0]     rs1_data;
    reg  [REG_ADDR_WIDTH-1:0] rs2_addr;
    wire [DATA_WIDTH-1:0]     rs2_data;

    // Instantiate Register File
    reg_file #(
        .DATA_WIDTH(DATA_WIDTH),
        .REG_ADDR_WIDTH(REG_ADDR_WIDTH)
    ) uut (
        .clk(clk),
        .reset(reset),
        .reg_write(reg_write),
        .rd_addr(rd_addr),
        .rd_data(rd_data),
        .rs1_addr(rs1_addr),
        .rs1_data(rs1_data),
        .rs2_addr(rs2_addr),
        .rs2_data(rs2_data)
    );

    // Clock Generation (10ns period)
    always #5 clk = ~clk;

    initial begin
        $dumpfile("sim/reg_file_wave.vcd");
        $dumpvars(0, tb_reg_file);

        clk = 0;
        reset = 1;
        reg_write = 0;
        rd_addr = 0;
        rd_data = 0;
        rs1_addr = 0;
        rs2_addr = 0;

        #12;
        reset = 0; // Release reset

        // Test 1: Write 0xABCD1234 into x1
        #10;
        reg_write = 1;
        rd_addr   = 5'd1;
        rd_data   = 32'hABCD_1234;

        // Test 2: Write 0x5555AAAA into x2
        #10;
        rd_addr   = 5'd2;
        rd_data   = 32'h5555_AAAA;

        // Test 3: Attempt to write 0xFFFFFFFF into x0 (should stay 0)
        #10;
        rd_addr   = 5'd0;
        rd_data   = 32'hFFFF_FFFF;

        // Test 4: Disable write and read x1 and x2
        #10;
        reg_write = 0;
        rs1_addr  = 5'd1;
        rs2_addr  = 5'd2;

        #5;
        $display("Read x1 (expected ABCD1234): 0x%h", rs1_data);
        $display("Read x2 (expected 5555AAAA): 0x%h", rs2_data);

        // Test 5: Read x0 (expected 0)
        #10;
        rs1_addr  = 5'd0;
        #5;
        $display("Read x0 (expected 00000000): 0x%h", rs1_data);

        #10;
        $finish;
    end

endmodule

sim/reg_file_wave.vcd
$date
	Thu Aug 13 22:49:48 2026
$end
$version
	Icarus Verilog
$end
$timescale
	1ps
$end
$scope module tb_reg_file $end
$var wire 32 ! rs2_data [31:0] $end
$var wire 32 " rs1_data [31:0] $end
$var reg 1 # clk $end
$var reg 5 $ rd_addr [4:0] $end
$var reg 32 % rd_data [31:0] $end
$var reg 1 & reg_write $end
$var reg 1 ' reset $end
$var reg 5 ( rs1_addr [4:0] $end
$var reg 5 ) rs2_addr [4:0] $end
$scope module uut $end
$var wire 1 # clk $end
$var wire 5 * rd_addr [4:0] $end
$var wire 32 + rd_data [31:0] $end
$var wire 1 & reg_write $end
$var wire 1 ' reset $end
$var wire 5 , rs1_addr [4:0] $end
$var wire 5 - rs2_addr [4:0] $end
$var wire 32 . rs2_data [31:0] $end
$var wire 32 / rs1_data [31:0] $end
$var integer 32 0 i [31:0] $end
$upscope $end
$upscope $end
$enddefinitions $end
#0
$dumpvars
b100000 0
b0 /
b0 .
b0 -
b0 ,
b0 +
b0 *
b0 )
b0 (
1'
0&
b0 %
b0 $
0#
b0 "
b0 !
$end
#5000
b100000 0
1#
#10000
0#
#12000
0'
#15000
1#
#20000
0#
#22000
b10101011110011010001001000110100 %
b10101011110011010001001000110100 +
b1 $
b1 *
1&
#25000
1#
#30000
0#
#32000
b1010101010101011010101010101010 %
b1010101010101011010101010101010 +
b10 $
b10 *
#35000
1#
#40000
0#
#42000
b11111111111111111111111111111111 %
b11111111111111111111111111111111 +
b0 $
b0 *
#45000
1#
#50000
0#
#52000
b1010101010101011010101010101010 !
b1010101010101011010101010101010 .
b10101011110011010001001000110100 "
b10101011110011010001001000110100 /
b10 )
b10 -
b1 (
b1 ,
0&
#55000
1#
#60000
0#
#65000
1#
#67000
b0 "
b0 /
b0 (
b0 ,
